{"appId":"winget_app_skyjake.Lagrange","appShortcutName":"Winget Application","appDisplayName":"Lagrange","authorId":"winget","releaseTagName":"winget-1.18.1","downloadUrls":{"1":{"installerType":"WindowsInstallerExe","asset":"","url":"https://github.com/microsoft/winget-pkgs/releases/download/winget-1.18.1/"},"0":{"installerType":"WindowsInstallerMsi","asset":"","url":"https://github.com/microsoft/winget-pkgs/releases/download/winget-1.18.1/"}},"install":{"win32":{"assetId":1,"exec":null,"installerArgs":null},"winarm":null,"linux":null,"linuxArm64":null,"linuxArm7":null,"android":null},"displayImages":[],"description":"Lagrange is a desktop GUI client for browsing Geminispace.\n\n\n","repo":{"author":"microsoft","repo":"winget-pkgs"},"version":"1.18.1","site":"https://github.com/skyjake/lagrange","source":"WinGet","license_or_tos":"BSD 2-Clause License","app_page":"https://github.com/skyjake/lagrange","resources":null}