{"appId":"winget_app_OtfriedCheong.Ipe","appShortcutName":"Winget Application","appDisplayName":"Ipe extensible drawing editor","authorId":"winget","releaseTagName":"winget-7.2.28","downloadUrls":{"0":{"installerType":"WindowsInstallerMsi","asset":"","url":""},"1":{"installerType":"WindowsInstallerExe","asset":"","url":"https://github.com/otfried/ipe/releases/download/v7.2.28/ipe-7.2.28-win64.zip"}},"install":{"win32":{"assetId":1,"exec":null,"installerArgs":null},"winarm":null,"linux":null,"linuxArm64":null,"linuxArm7":null,"android":null},"displayImages":[],"description":"A drawing editor for creating figures in PDF format\n\n\n","repo":{"author":"microsoft","repo":"winget-pkgs"},"version":"7.2.28","site":"https://otfried.org/","source":"WinGet","license_or_tos":"GPL","app_page":"https://ipe.otfried.org/","resources":null}