{"appId":"winget_app_TablePlus.TablePlus","appShortcutName":"Winget Application","appDisplayName":"TablePlus","authorId":"winget","releaseTagName":"winget-6.1.4","downloadUrls":{"0":{"installerType":"WindowsInstallerMsi","asset":"","url":"https://github.com/microsoft/winget-pkgs/releases/download/winget-6.1.4/"},"1":{"installerType":"WindowsInstallerExe","asset":"","url":"https://github.com/microsoft/winget-pkgs/releases/download/winget-6.1.4/"}},"install":{"win32":{"assetId":1,"exec":null,"installerArgs":null},"winarm":null,"linux":null,"linuxArm64":null,"linuxArm7":null,"android":null},"displayImages":[],"description":"Modern, native, and friendly GUI tool for relational databases: MySQL, PostgreSQL, SQLite & more\n\nModern, native client with intuitive GUI tools to create, access, query & edit multiple relational databases: MySQL, PostgreSQL, SQLite, Microsoft SQL Server, Amazon Redshift, MariaDB, CockroachDB, Vertica, and Redis.\nBuild 284 - Bug fixes and improvements\nRelease date: 9 Oct 2024\n1. [MySQL] Added SNI support.\n2. [PostgreSQL] Added support for disabling channel binding.\n3. [PostgreSQL] Added PostgreSQL 17 binaries.\n4. [SQLite] Updated SQLite to version 3.46.1.\n5. Other bug fixes and improvements.\nOlder change logs.\nBug report.\nUp coming features.","repo":{"author":"microsoft","repo":"winget-pkgs"},"version":"6.1.4","site":"https://tableplus.com/","source":"WinGet","license_or_tos":"Proprietary","app_page":"https://tableplus.com/windows","resources":null}