{"appId":"winget_app_ConceptworldCorporation.RecentX","appShortcutName":"Winget Application","appDisplayName":"RecentX","authorId":"winget","releaseTagName":"winget-5.0.26.0","downloadUrls":{"1":{"installerType":"WindowsInstallerMsi","asset":"","url":"https://github.com/microsoft/winget-pkgs/releases/download/winget-5.0.26.0/"},"0":{"installerType":"WindowsInstallerMsi","asset":"","url":"https://github.com/microsoft/winget-pkgs/releases/download/winget-5.0.26.0/"}},"install":{"win32":null,"winarm":null,"linux":null,"linuxArm64":null,"linuxArm7":null,"android":null},"displayImages":[],"description":"RecentX is a launcher for Windows designed to make your computing life joyful. It is packed with innovative ways of accessing your stuff on your Windows PC with lightning speed.\n\n\n","repo":{"author":"microsoft","repo":"winget-pkgs"},"version":"5.0.26.0","site":null,"source":"WinGet","license_or_tos":"MIT License","app_page":null,"resources":null}