{"appId":"winget_app_Microsoft.WindowsADK","appShortcutName":"Winget Application","appDisplayName":"Windows Assessment and Deployment Kit","authorId":"winget","releaseTagName":"winget-10.1.25398.1","downloadUrls":{"0":{"installerType":"WindowsInstallerMsi","asset":"","url":"https://github.com/microsoft/winget-pkgs/releases/download/winget-10.1.25398.1/"},"1":{"installerType":"WindowsInstallerMsi","asset":"","url":"https://github.com/microsoft/winget-pkgs/releases/download/winget-10.1.25398.1/"}},"install":{"win32":null,"winarm":null,"linux":null,"linuxArm64":null,"linuxArm7":null,"android":null},"displayImages":[],"description":"The Windows Assessment and Deployment Kit (Windows ADK) has the tools you need to customize Windows images for large-scale deployment, and to test the quality and performance of your system, its added components, and the applications running on it.\n\n\n","repo":{"author":"microsoft","repo":"winget-pkgs"},"version":"10.1.25398.1","site":"https://www.microsoft.com/","source":"WinGet","license_or_tos":"Proprietary","app_page":"https://docs.microsoft.com/windows-hardware/get-started/adk-install","resources":null}