{"appId":"winget_app_EXEMSI.MSIWrapper","appShortcutName":"Winget Application","appDisplayName":"MSI Wrapper","authorId":"winget","releaseTagName":"winget-11.0.53.0","downloadUrls":{"1":{"installerType":"WindowsInstallerMsi","asset":"","url":""},"0":{"installerType":"WindowsInstallerMsi","asset":"","url":""}},"install":{"win32":null,"winarm":null,"linux":null,"linuxArm64":null,"linuxArm7":null,"android":null},"displayImages":[],"description":"Convert executable installers to MSI packages fast and easy.\n\n\n- Minor updates.\n","repo":{"author":"microsoft","repo":"winget-pkgs"},"version":"11.0.53.0","site":"https://www.exemsi.com/","source":"exemsi.com","license_or_tos":"Freeware","resources":null,"verified":false}