{"appId":"winget_app_NI.ni_systemconfiguration","appShortcutName":"Winget Application","appDisplayName":"NI System Configuration","authorId":"winget","releaseTagName":"winget-24.5.0","downloadUrls":{"1":{"installerType":"WindowsInstallerExe","asset":"","url":"https://github.com/microsoft/winget-pkgs/releases/download/winget-24.5.0/"},"0":{"installerType":"WindowsInstallerMsi","asset":"","url":"https://github.com/microsoft/winget-pkgs/releases/download/winget-24.5.0/"}},"install":{"win32":{"assetId":1,"exec":null,"installerArgs":null},"winarm":null,"linux":null,"linuxArm64":null,"linuxArm7":null,"android":null},"displayImages":[],"description":"System Configuration includes utilities to help you monitor and control various NI devices in a system.\n\n\n","repo":{"author":"microsoft","repo":"winget-pkgs"},"version":"24.5.0","site":null,"source":"WinGet","license_or_tos":"NI General Purpose Software License Agreement","app_page":null,"resources":null}