{"appId":"winget_app_igoogolx.itun2socks","appShortcutName":"Winget Application","appDisplayName":"itun2socks","authorId":"winget","releaseTagName":"winget-1.20.3","downloadUrls":{"1":{"installerType":"WindowsInstallerExe","asset":"","url":"https://github.com/igoogolx/itun2socks/releases/download/v1.20.3/itun2socks_1.20.3_windows_amd64.zip"},"0":{"installerType":"WindowsInstallerMsi","asset":"","url":""}},"install":{"win32":{"assetId":1,"exec":null,"installerArgs":null},"winarm":null,"linux":null,"linuxArm64":null,"linuxArm7":null,"android":null},"displayImages":[],"description":"tun proxy tool\n\n\nChangelog\n- 059f48f V1.20.3 (#35)","repo":{"author":"microsoft","repo":"winget-pkgs"},"version":"1.20.3","site":"https://github.com/igoogolx","source":"WinGet","license_or_tos":"GPL License","app_page":"https://github.com/igoogolx/itun2socks","resources":null}