{"appId":"winget_app_JetBrains.dotUltimate","appShortcutName":"Winget Application","appDisplayName":"JetBrains dotUltimate","authorId":"winget","releaseTagName":"winget-2024.2.6","downloadUrls":{"1":{"installerType":"WindowsInstallerExe","asset":"","url":"https://download.jetbrains.com/resharper/dotUltimate.2024.2.6/JetBrains.dotUltimate.2024.2.6.exe"},"0":{"installerType":"WindowsInstallerMsi","asset":"","url":""}},"install":{"win32":{"assetId":1,"exec":null,"installerArgs":null},"winarm":null,"linux":null,"linuxArm64":null,"linuxArm7":null,"android":null},"displayImages":[],"description":"All .NET tools, ReSharper C++, and JetBrains Rider, together in one pack\n\n\nReSharper 2024.2.6 Has Been Released!\nReSharper\n- Support has been added for the Solution File Persistence Model, aka the .slnx format for solution files.\ndotTrace and dotMemory\n- There are no more random crashes on Linux (DTRC-30732).\ndotTrace\n- We’ve fixed an issue that caused the UI to freeze on opening a performance snapshot (DTRC-31199).\nTo see the whole list of fixed issues, please visit this page.","repo":{"author":"microsoft","repo":"winget-pkgs"},"version":"2024.2.6","site":"https://www.jetbrains.com/","source":"WinGet","license_or_tos":"Proprietary","app_page":"https://www.jetbrains.com/dotnet/","resources":null}