{"appId":"winget_app_YggdrasilNetwork.Yggdrasil","appShortcutName":"Winget Application","appDisplayName":"Yggdrasil Network","authorId":"winget","releaseTagName":"winget-0.5.5","downloadUrls":{"1":{"installerType":"WindowsInstallerExe","asset":"","url":"https://github.com/yggdrasil-network/yggdrasil-go/releases/download/v0.5.5/yggdrasil-0.5.5-x64.msi"},"0":{"installerType":"WindowsInstallerExe","asset":"","url":"https://github.com/yggdrasil-network/yggdrasil-go/releases/download/v0.5.5/yggdrasil-0.5.5-arm64.msi"}},"install":{"win32":{"assetId":1,"exec":null,"installerArgs":null},"winarm":{"assetId":0,"exec":null,"installerArgs":null},"linux":null,"linuxArm64":null,"linuxArm7":null,"android":null},"displayImages":[],"description":"The Yggdrasil network is a decentralized, peer-to-peer network that aims to create a more resilient and private internet infrastructure.\n\n\n","repo":{"author":"microsoft","repo":"winget-pkgs"},"version":"0.5.5","site":"https://yggdrasil-network.github.io","source":"WinGet","license_or_tos":"LGPLv3","resources":null,"verified":false}