{"appId":"winget_app_ToEverything.AFFiNE","appShortcutName":"Winget Application","appDisplayName":"AFFiNE","authorId":"winget","releaseTagName":"winget-0.17.5","downloadUrls":{"1":{"installerType":"WindowsInstallerExe","asset":"","url":"https://github.com/toeverything/AFFiNE/releases/download/v0.17.5/affine-0.17.5-stable-windows-x64.nsis.exe"},"0":{"installerType":"WindowsInstallerMsi","asset":"","url":""}},"install":{"win32":{"assetId":1,"exec":null,"installerArgs":null},"winarm":null,"linux":null,"linuxArm64":null,"linuxArm7":null,"android":null},"displayImages":[],"description":"A privacy-focused, local-first, open-source, and ready-to-use alternative for Notion & Miro. One hyper-fused platform for wildly creative minds.\n\nAFFiNE is an open-source, all-in-one workspace and an operating system for all the building blocks that assemble your knowledge base and much more -- wiki, knowledge management, presentation and digital assets. It's a better alternative to Notion and Miro.\n🐞 Bug Fixes\n- Message attachment merge - by @darkskygit in https://github.com/toeverything/AFFiNE/issues/8498 (b0527)\nView changes on GitHub","repo":{"author":"microsoft","repo":"winget-pkgs"},"version":"0.17.5","site":"https://github.com/toeverything","source":"AFFiNE","license_or_tos":"Proprietary","resources":null,"verified":false}