{"appId":"winget_app_Elcomsoft.PhoneViewer","appShortcutName":"Winget Application","appDisplayName":"Elcomsoft Phone Viewer","authorId":"winget","releaseTagName":"winget-5.52.39130.7201","downloadUrls":{"0":{"installerType":"WindowsInstallerMsi","asset":"","url":""},"1":{"installerType":"WindowsInstallerMsi","asset":"","url":""}},"install":{"win32":null,"winarm":null,"linux":null,"linuxArm64":null,"linuxArm7":null,"android":null},"displayImages":[],"description":"Elcomsoft Phone Viewer is a fast, lightweight forensic viewer for quickly accessing information extracted from mobile backups.\n\n\n","repo":{"author":"microsoft","repo":"winget-pkgs"},"version":"5.52.39130.7201","site":null,"source":"WinGet","license_or_tos":"Trialware","app_page":null,"resources":null}