{"appId":"winget_app_JakobDev.jdAppStreamEdit","appShortcutName":"Winget Application","appDisplayName":"jdAppStreamEdit","authorId":"winget","releaseTagName":"winget-9.1","downloadUrls":{"0":{"installerType":"WindowsInstallerMsi","asset":"","url":"https://github.com/microsoft/winget-pkgs/releases/download/winget-9.1/"},"1":{"installerType":"WindowsInstallerMsi","asset":"","url":"https://github.com/microsoft/winget-pkgs/releases/download/winget-9.1/"}},"install":{"win32":null,"winarm":null,"linux":null,"linuxArm64":null,"linuxArm7":null,"android":null},"displayImages":[],"description":"A graphical Program to create and edit AppStream files\n\n\n","repo":{"author":"microsoft","repo":"winget-pkgs"},"version":"9.1","site":null,"source":"WinGet","license_or_tos":"GNU GPLv3","app_page":"https://jakobdev.codeberg.page/work/app/jdAppStreamEdit","resources":null}