{"appId":"winget_app_Novaquark.DualUniverse","appShortcutName":"Winget Application","appDisplayName":"Dual Universe","authorId":"winget","releaseTagName":"winget-1.0","downloadUrls":{"1":{"installerType":"WindowsInstallerExe","asset":"","url":"https://installer-prod.dualthegame.com/prod/dual-installer.exe"},"0":{"installerType":"WindowsInstallerMsi","asset":"","url":""}},"install":{"win32":{"assetId":1,"exec":null,"installerArgs":null},"winarm":null,"linux":null,"linuxArm64":null,"linuxArm7":null,"android":null},"displayImages":[],"description":"Dual Universe is a forward-thinking online game featuring a persistent and shared universe made with next-generation voxels.\n\nDual Universe is a forward-thinking online game featuring a persistent and shared universe made with next-generation voxels.\nAs a true precursor to the metaverse, the game world is fully editable, and the game experience is entirely driven by its players.\nDual Universe is currently in public beta and reaching the final stretch toward launch.\n","repo":{"author":"microsoft","repo":"winget-pkgs"},"version":"1.0","site":"https://www.novaquark.com","source":"WinGet","license_or_tos":"Proprietary","resources":null,"verified":false}