{"appId":"winget_app_jbreland.autoflac","appShortcutName":"Winget Application","appDisplayName":"AutoFLAC","authorId":"winget","releaseTagName":"winget-1.2","downloadUrls":{"0":{"installerType":"WindowsInstallerMsi","asset":"","url":""},"1":{"installerType":"WindowsInstallerExe","asset":"","url":"https://www.legroom.net/files/software/autoflac12.exe"}},"install":{"win32":{"assetId":1,"exec":null,"installerArgs":null},"winarm":null,"linux":null,"linuxArm64":null,"linuxArm7":null,"android":null},"displayImages":[],"description":"AutoFLAC is a script that works in conjunction with Exact Audio Copy to automate the process of backing and restoring your audio CD collection using the FLAC media format\n\n\n","repo":{"author":"microsoft","repo":"winget-pkgs"},"version":"1.2","site":null,"source":"Jared Breland","license_or_tos":"gpl","resources":null,"verified":false}