{"appId":"winget_app_quick_lint.quick_lint_js","appShortcutName":"Winget Application","appDisplayName":"quick-lint-js","authorId":"winget","releaseTagName":"winget-3.1.0.0","downloadUrls":{"1":{"installerType":"WindowsInstallerMsi","asset":"","url":""},"0":{"installerType":"WindowsInstallerMsi","asset":"","url":""}},"install":{"win32":null,"winarm":null,"linux":null,"linuxArm64":null,"linuxArm7":null,"android":null},"displayImages":[],"description":"Find bugs in JavaScript programs.\n\n\n","repo":{"author":"microsoft","repo":"winget-pkgs"},"version":"3.1.0.0","site":null,"source":"WinGet","license_or_tos":"GPL-3.0-or-later,MIT,BSL-1.0,Apache-2.0,ZPL-2.1,Public Domain,ISC,BSD-2-Clause,MIT-CMU,LGPL-2.1-or-later,GPL-2.0-or-later,BSD-3-Clause","resources":null,"verified":false}