{"appId":"winget_app_UweSieber.UsbDriveInfo","appShortcutName":"Winget Application","appDisplayName":"UsbDriveInfo","authorId":"winget","releaseTagName":"winget-5.5.8","downloadUrls":{"1":{"installerType":"WindowsInstallerExe","asset":"","url":"https://www.uwe-sieber.de/files/UsbDriveInfo.zip"},"0":{"installerType":"WindowsInstallerMsi","asset":"","url":""}},"install":{"win32":{"assetId":1,"exec":null,"installerArgs":null},"winarm":null,"linux":null,"linuxArm64":null,"linuxArm7":null,"android":null},"displayImages":[],"description":"Information about USB drives.\n\n\n","repo":{"author":"microsoft","repo":"winget-pkgs"},"version":"5.5.8","site":null,"source":"WinGet","license_or_tos":"Proprietary","app_page":null,"resources":null}