{"appId":"winget_app_bee_san.Ares","appShortcutName":"Winget Application","appDisplayName":"Ares","authorId":"winget","releaseTagName":"winget-0.10.0","downloadUrls":{"0":{"installerType":"WindowsInstallerMsi","asset":"","url":""},"1":{"installerType":"WindowsInstallerMsi","asset":"","url":""}},"install":{"win32":null,"winarm":null,"linux":null,"linuxArm64":null,"linuxArm7":null,"android":null},"displayImages":[],"description":"Automated decoding of encrypted text without knowing the key or ciphers used.\n\nAres is the next generation of decoding tools, built by the same people that brought you Ciphey.\nWe fully intend to replace Ciphey with Ares.\n","repo":{"author":"microsoft","repo":"winget-pkgs"},"version":"0.10.0","site":"https://github.com/bee-san","source":"WinGet","license_or_tos":"MIT","resources":null,"verified":false}