{"appId":"winget_app_Redisant.ModbusMasterEmulator","appShortcutName":"Winget Application","appDisplayName":"Modbus Master Emulator","authorId":"winget","releaseTagName":"winget-2.1.5.6","downloadUrls":{"1":{"installerType":"WindowsInstallerExe","asset":"","url":"https://github.com/chenjing1294/mme-release/releases/download/v2.1.5.6/MME-2.1.5.6-windows.zip"},"0":{"installerType":"WindowsInstallerMsi","asset":"","url":""}},"install":{"win32":{"assetId":1,"exec":null,"installerArgs":null},"winarm":null,"linux":null,"linuxArm64":null,"linuxArm7":null,"android":null},"displayImages":[],"description":"Create multiple connections at the same time, monitor multiple Modbus slave registers, and quickly debug your slave devices.\n\n\n- [Improved] Upgrade dependencies\n- [Fixed] Fix some issues","repo":{"author":"microsoft","repo":"winget-pkgs"},"version":"2.1.5.6","site":"https://www.redisant.com/","source":"WinGet","license_or_tos":"Proprietary","resources":null,"verified":false}