{"appId":"winget_app_Twitch.TwitchCLI","appShortcutName":"Winget Application","appDisplayName":"Twitch CLI","authorId":"winget","releaseTagName":"winget-1.1.24","downloadUrls":{"1":{"installerType":"WindowsInstallerMsi","asset":"","url":"https://github.com/microsoft/winget-pkgs/releases/download/winget-1.1.24/"},"0":{"installerType":"WindowsInstallerMsi","asset":"","url":"https://github.com/microsoft/winget-pkgs/releases/download/winget-1.1.24/"}},"install":{"win32":null,"winarm":null,"linux":null,"linuxArm64":null,"linuxArm7":null,"android":null},"displayImages":[],"description":"The official Twitch CLI to make developing on Twitch easier.\n\n\nThank you to @BarryCarlyon for fixing the critical issue.","repo":{"author":"microsoft","repo":"winget-pkgs"},"version":"1.1.24","site":"https://dev.twitch.tv/","source":"WinGet","license_or_tos":"Apache-2.0","app_page":"https://dev.twitch.tv/docs/cli/","resources":null}