{"appId":"winget_app_JetBrains.dotTrace","appShortcutName":"Winget Application","appDisplayName":"JetBrains dotTrace","authorId":"winget","releaseTagName":"winget-2023.3.4","downloadUrls":{"1":{"installerType":"WindowsInstallerExe","asset":"","url":"https://download-cdn.jetbrains.com/resharper/dotUltimate.2023.3.4/JetBrains.dotTrace.2023.3.4.web.exe"},"0":{"installerType":"WindowsInstallerMsi","asset":"","url":""}},"install":{"win32":{"assetId":1,"exec":null,"installerArgs":null},"winarm":null,"linux":null,"linuxArm64":null,"linuxArm7":null,"android":null},"displayImages":[],"description":".NET Performance Profiler\n\n\n","repo":{"author":"microsoft","repo":"winget-pkgs"},"version":"2023.3.4","site":"https://www.jetbrains.com/","source":"WinGet","license_or_tos":"Proprietary","app_page":"https://www.jetbrains.com/profiler/","resources":null}