{"appId":"winget_app_DelugeTeam.Deluge","appShortcutName":"Winget Application","appDisplayName":"Deluge BitTorrent Client","authorId":"winget","releaseTagName":"winget-2.1.1","downloadUrls":{"0":{"installerType":"WindowsInstallerMsi","asset":"","url":""},"1":{"installerType":"WindowsInstallerExe","asset":"","url":"http://download.deluge-torrent.org/windows/deluge-2.1.1-win64-setup.exe"}},"install":{"win32":{"assetId":1,"exec":null,"installerArgs":null},"winarm":null,"linux":null,"linuxArm64":null,"linuxArm7":null,"android":null},"displayImages":[],"description":"Deluge is a lightweight, Free Software, cross-platform BitTorrent client.\n\n\n","repo":{"author":"microsoft","repo":"winget-pkgs"},"version":"2.1.1","site":null,"source":"WinGet","license_or_tos":"GNU GPL v3","resources":null,"verified":false}