{"appId":"winget_app_HydrologicEngineeringCenter.HEC_DSSVue","appShortcutName":"Winget Application","appDisplayName":"HEC-DSSVue","authorId":"winget","releaseTagName":"winget-3.2.3","downloadUrls":{"1":{"installerType":"WindowsInstallerMsi","asset":"","url":""},"0":{"installerType":"WindowsInstallerMsi","asset":"","url":""}},"install":{"win32":null,"winarm":null,"linux":null,"linuxArm64":null,"linuxArm7":null,"android":null},"displayImages":[],"description":"HEC-DSSVue is a Java-based visual utilities program that allows users to plot, tabulate, edit, and manipulate data in a HEC-DSS database file.\n\n\n","repo":{"author":"microsoft","repo":"winget-pkgs"},"version":"3.2.3","site":null,"source":"WinGet","license_or_tos":"Proprietary","app_page":null,"resources":null}