{"appId":"winget_app_Task.Task","appShortcutName":"Winget Application","appDisplayName":"Task","authorId":"winget","releaseTagName":"winget-3.39.2","downloadUrls":{"0":{"installerType":"WindowsInstallerExe","asset":"","url":"https://github.com/go-task/task/releases/download/v3.39.2/task_windows_arm64.zip"},"1":{"installerType":"WindowsInstallerExe","asset":"","url":"https://github.com/go-task/task/releases/download/v3.39.2/task_windows_amd64.zip"}},"install":{"win32":{"assetId":1,"exec":null,"installerArgs":null},"winarm":{"assetId":0,"exec":null,"installerArgs":null},"linux":null,"linuxArm64":null,"linuxArm7":null,"android":null},"displayImages":[],"description":"A task runner / simpler Make alternative written in Go\n\nTask is a task runner / build tool that aims to be simpler and easier to use than, for example, GNU Make.\n","repo":{"author":"microsoft","repo":"winget-pkgs"},"version":"3.39.2","site":"https://taskfile.dev/","source":"WinGet","license_or_tos":"MIT","resources":null,"verified":false}