{"appId":"winget_app_Logitech.SetPoint","appShortcutName":"Winget Application","appDisplayName":"Logitech SetPoint","authorId":"winget","releaseTagName":"winget-6.90.66","downloadUrls":{"0":{"installerType":"WindowsInstallerMsi","asset":"","url":""},"1":{"installerType":"WindowsInstallerExe","asset":"","url":"https://download01.logi.com/web/ftp/pub/techsupport/mouse/SetPoint6.90.66_64.exe"}},"install":{"win32":{"assetId":1,"exec":null,"installerArgs":null},"winarm":null,"linux":null,"linuxArm64":null,"linuxArm7":null,"android":null},"displayImages":[],"description":"Logitech SetPoint lets you customize your mouse, keyboard, touchpad and number pad settings in Windows.\n\n\n","repo":{"author":"microsoft","repo":"winget-pkgs"},"version":"6.90.66","site":"https://www.logitech.com/","source":"WinGet","license_or_tos":"Copyright (c) 2005-2019 Logitech. All Rights Reserved.","resources":null,"verified":false}