{"appId":"winget_app_StudioRack.StudioRack","appShortcutName":"Winget Application","appDisplayName":"StudioRack App","authorId":"winget","releaseTagName":"winget-0.1.0","downloadUrls":{"0":{"installerType":"WindowsInstallerMsi","asset":"","url":"https://github.com/microsoft/winget-pkgs/releases/download/winget-0.1.0/"},"1":{"installerType":"WindowsInstallerMsi","asset":"","url":"https://github.com/microsoft/winget-pkgs/releases/download/winget-0.1.0/"}},"install":{"win32":null,"winarm":null,"linux":null,"linuxArm64":null,"linuxArm7":null,"android":null},"displayImages":[],"description":"Audio plugin app, searchable list of plugins to install and share\n\n\n","repo":{"author":"microsoft","repo":"winget-pkgs"},"version":"0.1.0","site":null,"source":"WinGet","license_or_tos":"MIT","app_page":null,"resources":null}