{"appId":"winget_app_JetBrains.CLion","appShortcutName":"Winget Application","appDisplayName":"CLion","authorId":"winget","releaseTagName":"winget-2024.2.3","downloadUrls":{"1":{"installerType":"WindowsInstallerMsi","asset":"","url":""},"0":{"installerType":"WindowsInstallerExe","asset":"","url":"https://download.jetbrains.com/cpp/CLion-2024.2.3-aarch64.exe"}},"install":{"win32":null,"winarm":{"assetId":0,"exec":null,"installerArgs":null},"linux":null,"linuxArm64":null,"linuxArm7":null,"android":null},"displayImages":[],"description":"A cross-platform IDE for C and C++\n\nA powerful IDE from JetBrains helps you develop in C and C++ on Linux, macOS and Windows.\nThe CLion 2024.2.3 bug-fix update is now available.\nThe highlights include:\n- Copying in the editor again works as intended when using CLion Nova and developing remotely with the thin client.\n- When enabled in the CMake settings, the Reload CMake project on editing CMakeLists.txt or other CMake configuration files option retains its state after CLion’s main Settings menu is reopened.\n- The debugger now correctly displays elements of std::list when using an ABI predating С++11.\n- If selected in the old terminal settings, the vertical cursor is retained when the Terminal tool window is reopened.\n- The editor pane can again be resized after placing the tab on the left and reloading the IDE.\nPlease share your feedback and report any issues to our issue tracker.","repo":{"author":"microsoft","repo":"winget-pkgs"},"version":"2024.2.3","site":"https://www.jetbrains.com/","source":"WinGet","license_or_tos":"Proprietary","resources":null,"verified":false}