{"appId":"winget_app_deviceinsight.kafkactl_azure_plugin","appShortcutName":"Winget Application","appDisplayName":"kafkactl-azure-plugin","authorId":"winget","releaseTagName":"winget-1.1.1","downloadUrls":{"0":{"installerType":"WindowsInstallerExe","asset":"","url":"https://github.com/deviceinsight/kafkactl-plugins/releases/download/v1.1.1/kafkactl-azure-plugin_1.1.1_windows_arm64.zip"},"1":{"installerType":"WindowsInstallerExe","asset":"","url":"https://github.com/deviceinsight/kafkactl-plugins/releases/download/v1.1.1/kafkactl-azure-plugin_1.1.1_windows_amd64.zip"}},"install":{"win32":{"assetId":1,"exec":null,"installerArgs":null},"winarm":{"assetId":0,"exec":null,"installerArgs":null},"linux":null,"linuxArm64":null,"linuxArm7":null,"android":null},"displayImages":[],"description":"Azure Plugin for kafkactl\n\n\n","repo":{"author":"microsoft","repo":"winget-pkgs"},"version":"1.1.1","site":null,"source":"WinGet","license_or_tos":"Apache-2.0","app_page":"https://www.device-insight.com/","resources":null}