{"appId":"winget_app_HydraLauncher.Hydra","appShortcutName":"Winget Application","appDisplayName":"Hydra","authorId":"winget","releaseTagName":"winget-2.1.7","downloadUrls":{"1":{"installerType":"WindowsInstallerExe","asset":"","url":"https://github.com/hydralauncher/hydra/releases/download/v2.1.7/hydralauncher-2.1.7-setup.exe"},"0":{"installerType":"WindowsInstallerMsi","asset":"","url":""}},"install":{"win32":{"assetId":1,"exec":null,"installerArgs":null},"winarm":null,"linux":null,"linuxArm64":null,"linuxArm7":null,"android":null},"displayImages":[],"description":"Hydra is a game launcher with its own embedded bittorrent client and a self-managed repack scraper.\n\nHydra is a game launcher with its own embedded bittorrent client and a self-managed repack scraper.\n- Add missing EN translation inside friends modal\n- Update URLs to fix some ISP blocking connection to our backend","repo":{"author":"microsoft","repo":"winget-pkgs"},"version":"2.1.7","site":"https://github.com/hydralauncher","source":"WinGet","license_or_tos":"MIT","resources":null,"verified":false}