{"appId":"winget_app_Kubernetes.kind","appShortcutName":"Winget Application","appDisplayName":"kind","authorId":"winget","releaseTagName":"winget-0.24.0","downloadUrls":{"0":{"installerType":"WindowsInstallerMsi","asset":"","url":"https://github.com/microsoft/winget-pkgs/releases/download/winget-0.24.0/"},"1":{"installerType":"WindowsInstallerMsi","asset":"","url":"https://github.com/microsoft/winget-pkgs/releases/download/winget-0.24.0/"}},"install":{"win32":null,"winarm":null,"linux":null,"linuxArm64":null,"linuxArm7":null,"android":null},"displayImages":[],"description":"A tool for running local Kubernetes clusters using Docker container \"nodes\"\n\n\n","repo":{"author":"microsoft","repo":"winget-pkgs"},"version":"0.24.0","site":"https://github.com/kubernetes-sigs","source":"WinGet","license_or_tos":"Apache License 2.0","app_page":"https://kind.sigs.k8s.io/","resources":null}