{"appId":"winget_app_TominLab.WonderPen","appShortcutName":"Winget Application","appDisplayName":"WonderPen","authorId":"winget","releaseTagName":"winget-2.5.6","downloadUrls":{"1":{"installerType":"WindowsInstallerExe","asset":"","url":"https://file.tominlab.com/WonderPen/2.5/WonderPen_win_installer_x64_2.5.6(7500).exe"},"0":{"installerType":"WindowsInstallerMsi","asset":"","url":""}},"install":{"win32":{"assetId":1,"exec":null,"installerArgs":null},"winarm":null,"linux":null,"linuxArm64":null,"linuxArm7":null,"android":null},"displayImages":[],"description":"App for writing long stories\n\nWonderPen is a professional writing app with a focused and fluid writing experience\n- Improved cloud sync method\n- Some details optimization","repo":{"author":"microsoft","repo":"winget-pkgs"},"version":"2.5.6","site":"https://www.tominlab.com/en","source":"WinGet","license_or_tos":"Proprietary","app_page":"https://www.tominlab.com/en/wonderpen","resources":null}