{"appId":"winget_app_BeagleSoftware.BeTL","appShortcutName":"Winget Application","appDisplayName":"BeagleEditor Toolchain (BeTL)","authorId":"winget","releaseTagName":"winget-0.1.0","downloadUrls":{"0":{"installerType":"WindowsInstallerMsi","asset":"","url":""},"1":{"installerType":"WindowsInstallerExe","asset":"","url":"https://github.com/beaglesoftware/betl/releases/download/0.1.0-pre/BeTL-0.1.0-Installer.exe"}},"install":{"win32":{"assetId":1,"exec":null,"installerArgs":null},"winarm":null,"linux":null,"linuxArm64":null,"linuxArm7":null,"android":null},"displayImages":[],"description":"Tools for BeagleEditor, all in one place!\n\n\n","repo":{"author":"microsoft","repo":"winget-pkgs"},"version":"0.1.0","site":null,"source":"BeagleSoftware","license_or_tos":"MIT License","resources":null,"verified":false}