{"appId":"winget_app_ironfede.StructuredStorageXplorer","appShortcutName":"Winget Application","appDisplayName":"Structured Storage Xplorer","authorId":"winget","releaseTagName":"winget-2.3.1.0","downloadUrls":{"0":{"installerType":"WindowsInstallerMsi","asset":"","url":"https://github.com/microsoft/winget-pkgs/releases/download/winget-2.3.1.0/"},"1":{"installerType":"WindowsInstallerMsi","asset":"","url":"https://github.com/microsoft/winget-pkgs/releases/download/winget-2.3.1.0/"}},"install":{"win32":null,"winarm":null,"linux":null,"linuxArm64":null,"linuxArm7":null,"android":null},"displayImages":[],"description":"Microsoft Compound File .net component - pure C# - netstandard 2.0\n\n\n","repo":{"author":"microsoft","repo":"winget-pkgs"},"version":"2.3.1.0","site":"https://github.com/ironfede","source":"WinGet","license_or_tos":"MPL-2.0","app_page":"https://github.com/ironfede/openmcdf","resources":null}