{"appId":"winget_app_Yamaha.SteinbergUSBDriver","appShortcutName":"Winget Application","appDisplayName":"Steinberg USB Driver","authorId":"winget","releaseTagName":"winget-2.1.7","downloadUrls":{"1":{"installerType":"WindowsInstallerExe","asset":"","url":"https://download.steinberg.net/downloads_hardware/Yamaha_Steinberg_USB_Driver/Win/2.1.7/YSUSB_V217_Win.zip"},"0":{"installerType":"WindowsInstallerMsi","asset":"","url":""}},"install":{"win32":{"assetId":1,"exec":null,"installerArgs":null},"winarm":null,"linux":null,"linuxArm64":null,"linuxArm7":null,"android":null},"displayImages":[],"description":"Yamaha Steinberg USB Driver\n\nThe Yamaha Steinberg USB Driver enables communication between a USB device (which is compatible with the Yamaha Steinberg USB Driver) and your computer.\n","repo":{"author":"microsoft","repo":"winget-pkgs"},"version":"2.1.7","site":null,"source":"WinGet","license_or_tos":"Proprietary","app_page":null,"resources":null}