{"appId":"winget_app_DaxStudio.DaxStudio","appShortcutName":"Winget Application","appDisplayName":"DAX Studio","authorId":"winget","releaseTagName":"winget-3.2.1","downloadUrls":{"1":{"installerType":"WindowsInstallerExe","asset":"","url":"https://github.com/microsoft/winget-pkgs/releases/download/winget-3.2.1/"},"0":{"installerType":"WindowsInstallerMsi","asset":"","url":"https://github.com/microsoft/winget-pkgs/releases/download/winget-3.2.1/"}},"install":{"win32":{"assetId":1,"exec":null,"installerArgs":null},"winarm":null,"linux":null,"linuxArm64":null,"linuxArm7":null,"android":null},"displayImages":[],"description":"The ultimate tool for working with DAX queries\n\n\n","repo":{"author":"microsoft","repo":"winget-pkgs"},"version":"3.2.1","site":"https://github.com/DaxStudio/DaxStudio","source":"WinGet","license_or_tos":"Microsoft Reciprocal License (Ms-RL)","app_page":"https://daxstudio.org","resources":null}