{"appId":"winget_app_the_sz.Trion","appShortcutName":"Winget Application","appDisplayName":"Trion","authorId":"winget","releaseTagName":"winget-1.22","downloadUrls":{"0":{"installerType":"WindowsInstallerMsi","asset":"","url":""},"1":{"installerType":"WindowsInstallerMsi","asset":"","url":""}},"install":{"win32":null,"winarm":null,"linux":null,"linuxArm64":null,"linuxArm7":null,"android":null},"displayImages":[],"description":"Serial port monitor which supports ANSI colors, save received data and logging to a text file\n\nThis serial port terminal application supports ANSI colors, save received data and logging to a text file.\n","repo":{"author":"microsoft","repo":"winget-pkgs"},"version":"1.22","site":"https://the-sz.com/","source":"WinGet","license_or_tos":"Proprietary","resources":null,"verified":false}