{"appId":"winget_app_amacneil.dbmate","appShortcutName":"Winget Application","appDisplayName":"Dbmate","authorId":"winget","releaseTagName":"winget-2.13.0","downloadUrls":{"1":{"installerType":"WindowsInstallerMsi","asset":"","url":"https://github.com/microsoft/winget-pkgs/releases/download/winget-2.13.0/"},"0":{"installerType":"WindowsInstallerMsi","asset":"","url":"https://github.com/microsoft/winget-pkgs/releases/download/winget-2.13.0/"}},"install":{"win32":null,"winarm":null,"linux":null,"linuxArm64":null,"linuxArm7":null,"android":null},"displayImages":[],"description":"A lightweight, framework-agnostic database migration tool\n\n\nWhat's Changed\n- Bump ip from 2.0.0 to 2.0.1 in /typescript by @dependabot in #521\n- Bump softprops/action-gh-release from 1 to 2 by @dependabot in #525\n- Bump golang from 1.22.0 to 1.22.1 by @dependabot in #524\n- Update dependencies by @amacneil in #526\nFull Changelog:","repo":{"author":"microsoft","repo":"winget-pkgs"},"version":"2.13.0","site":"https://github.com/amacneil","source":"WinGet","license_or_tos":"MIT","app_page":null,"resources":null}