{"appId":"winget_app_AVS.InstallPackComplete","appShortcutName":"Winget Application","appDisplayName":"AVS4YOU Programs Installation","authorId":"winget","releaseTagName":"winget-5.7.2.189","downloadUrls":{"0":{"installerType":"WindowsInstallerMsi","asset":"","url":"https://github.com/microsoft/winget-pkgs/releases/download/winget-5.7.2.189/"},"1":{"installerType":"WindowsInstallerMsi","asset":"","url":"https://github.com/microsoft/winget-pkgs/releases/download/winget-5.7.2.189/"}},"install":{"win32":null,"winarm":null,"linux":null,"linuxArm64":null,"linuxArm7":null,"android":null},"displayImages":[],"description":"Get all AVS4YOU software in 1 installation package.\n\n\n","repo":{"author":"microsoft","repo":"winget-pkgs"},"version":"5.7.2.189","site":null,"source":"WinGet","license_or_tos":"Proprietary","app_page":null,"resources":null}