{"appId":"winget_app_Spacemesh.Spacemesh","appShortcutName":"Winget Application","appDisplayName":"Spacemesh","authorId":"winget","releaseTagName":"winget-1.6.5","downloadUrls":{"1":{"installerType":"WindowsInstallerMsi","asset":"","url":"https://github.com/microsoft/winget-pkgs/releases/download/winget-1.6.5/"},"0":{"installerType":"WindowsInstallerMsi","asset":"","url":"https://github.com/microsoft/winget-pkgs/releases/download/winget-1.6.5/"}},"install":{"win32":null,"winarm":null,"linux":null,"linuxArm64":null,"linuxArm7":null,"android":null},"displayImages":[],"description":"Smesher UI + Wallet\n\n\n","repo":{"author":"microsoft","repo":"winget-pkgs"},"version":"1.6.5","site":"https://github.com/spacemeshos","source":"WinGet","license_or_tos":"Apache-2.0","app_page":"https://github.com/spacemeshos/smapp","resources":null}