{"appId":"winget_app_IceChat.IceChat","appShortcutName":"Winget Application","appDisplayName":"IceChat","authorId":"winget","releaseTagName":"winget-9.53","downloadUrls":{"1":{"installerType":"WindowsInstallerExe","asset":"","url":"https://www.icechat.net/site/download.php?did=18"},"0":{"installerType":"WindowsInstallerMsi","asset":"","url":""}},"install":{"win32":{"assetId":1,"exec":null,"installerArgs":null},"winarm":null,"linux":null,"linuxArm64":null,"linuxArm7":null,"android":null},"displayImages":[],"description":"IceChat is an open source IRC Client written in C# using WinForms.\n\n\n","repo":{"author":"microsoft","repo":"winget-pkgs"},"version":"9.53","site":null,"source":"WinGet","license_or_tos":"GNU General Public License, version 2","resources":null,"verified":false}