{"appId":"winget_app_OSGeo.GeoServer","appShortcutName":"Winget Application","appDisplayName":"GeoServer","authorId":"winget","releaseTagName":"winget-2.24.2","downloadUrls":{"0":{"installerType":"WindowsInstallerMsi","asset":"","url":"https://github.com/microsoft/winget-pkgs/releases/download/winget-2.24.2/"},"1":{"installerType":"WindowsInstallerExe","asset":"","url":"https://github.com/microsoft/winget-pkgs/releases/download/winget-2.24.2/"}},"install":{"win32":{"assetId":1,"exec":null,"installerArgs":null},"winarm":null,"linux":null,"linuxArm64":null,"linuxArm7":null,"android":null},"displayImages":[],"description":"GeoServer is an open source software server written in Java that allows users to share and edit geospatial data.\n\n\n","repo":{"author":"microsoft","repo":"winget-pkgs"},"version":"2.24.2","site":"http://geoserver.org/","source":"WinGet","license_or_tos":"GNU General Public License, Version 2","app_page":"http://geoserver.org/","resources":null}