{"appId":"winget_app_MiKTeX.MiKTeX","appShortcutName":"Winget Application","appDisplayName":"MiKTeX","authorId":"winget","releaseTagName":"winget-24.1","downloadUrls":{"0":{"installerType":"WindowsInstallerMsi","asset":"","url":"https://github.com/microsoft/winget-pkgs/releases/download/winget-24.1/"},"1":{"installerType":"WindowsInstallerExe","asset":"","url":"https://github.com/microsoft/winget-pkgs/releases/download/winget-24.1/"}},"install":{"win32":{"assetId":1,"exec":null,"installerArgs":null},"winarm":null,"linux":null,"linuxArm64":null,"linuxArm7":null,"android":null},"displayImages":[],"description":"A modern TeX distribution for Windows, Linux and macOS.\n\nMiKTeX is a modern TeX distribution for Windows, Linux and macOS.\nMiKTeX's integrated package manager installs missing components from the Internet, if required. This allows you to keep your TeX installation as minimal as possible (“Just enough TeX”).\nMiKTeX is open source. You are welcome to redistribute MiKTeX under certain conditions.\n","repo":{"author":"microsoft","repo":"winget-pkgs"},"version":"24.1","site":"https://miktex.org/","source":"WinGet","license_or_tos":"Freeware","app_page":"https://miktex.org/download","resources":null}