{"appId":"winget_app_egoist.devdocs_desktop","appShortcutName":"Winget Application","appDisplayName":"DevDocs","authorId":"winget","releaseTagName":"winget-0.7.2","downloadUrls":{"0":{"installerType":"WindowsInstallerMsi","asset":"","url":""},"1":{"installerType":"WindowsInstallerExe","asset":"","url":"https://github.com/egoist/devdocs-desktop/releases/download/v0.7.2/DevDocs-0.7.2.exe"}},"install":{"win32":{"assetId":1,"exec":null,"installerArgs":null},"winarm":null,"linux":null,"linuxArm64":null,"linuxArm7":null,"android":null},"displayImages":[],"description":"A full-featured desktop app for DevDocs.io.\n\nDevDocs.io combines multiple API documentations in a fast, organized, and searchable interface.\nThis is an unofficial desktop app for it.\nChanges\n- Upgraded to Electron 12, so it could run on Mac M1.\n- Now the Mac app is not signed due to that my mac app developer program has expired and I've no intention to renew it (which costs $99/y)\nInstall\n- macOS\n- Windows\n- Installer\n- Portable\n- Linux\n- AppImage (Recommended)\n- deb","repo":{"author":"microsoft","repo":"winget-pkgs"},"version":"0.7.2","site":"https://github.com/egoist/devdocs-desktop","source":"WinGet","license_or_tos":"MIT License","resources":null,"verified":false}