{"appId":"winget_app_Dialpad.Dialpad","appShortcutName":"Winget Application","appDisplayName":"Dialpad","authorId":"winget","releaseTagName":"winget-2409.4.0","downloadUrls":{"1":{"installerType":"WindowsInstallerMsi","asset":"","url":"https://github.com/microsoft/winget-pkgs/releases/download/winget-2409.4.0/"},"0":{"installerType":"WindowsInstallerMsi","asset":"","url":"https://github.com/microsoft/winget-pkgs/releases/download/winget-2409.4.0/"}},"install":{"win32":null,"winarm":null,"linux":null,"linuxArm64":null,"linuxArm7":null,"android":null},"displayImages":[],"description":"Dialpad for Windows enables Windows users to access the Dialpad service.\n\nDialpad for Windows enables Windows users to access the Dialpad service.\n","repo":{"author":"microsoft","repo":"winget-pkgs"},"version":"2409.4.0","site":"https://www.dialpad.com/","source":"WinGet","license_or_tos":"Proprietary","app_page":"https://www.dialpad.com/download","resources":null}